{
    "key": "group_624b404076b53",
    "title": "Contact Details",
    "fields": [
        {
            "key": "field_62ab7e3fda45f",
            "label": "Options",
            "name": "options",
            "type": "group",
            "instructions": "",
            "required": 0,
            "conditional_logic": 0,
            "wrapper": {
                "width": "",
                "class": "",
                "id": ""
            },
            "layout": "block",
            "wpml_cf_preferences": 1,
            "sub_fields": [
                {
                    "key": "field_62ab7e43da460",
                    "label": "Background Colour",
                    "name": "background_colour",
                    "type": "select",
                    "instructions": "",
                    "required": 0,
                    "conditional_logic": 0,
                    "wrapper": {
                        "width": "",
                        "class": "",
                        "id": ""
                    },
                    "choices": {
                        "#FFF": "White",
                        "#f7f9fa": "Light Gray",
                        "#f0f3f5": "Dark Gray"
                    },
                    "default_value": false,
                    "allow_null": 0,
                    "multiple": 0,
                    "ui": 1,
                    "ajax": 0,
                    "return_format": "value",
                    "wpml_cf_preferences": 1,
                    "placeholder": ""
                }
            ]
        },
        {
            "key": "field_624b404079570",
            "label": "Heading",
            "name": "heading",
            "type": "text",
            "instructions": "",
            "required": 0,
            "conditional_logic": 0,
            "wrapper": {
                "width": "",
                "class": "",
                "id": ""
            },
            "wpml_cf_preferences": 1,
            "default_value": "",
            "placeholder": "",
            "prepend": "",
            "append": "",
            "maxlength": ""
        },
        {
            "key": "field_624b404079577",
            "label": "Columns",
            "name": "columns",
            "type": "repeater",
            "instructions": "",
            "required": 0,
            "conditional_logic": 0,
            "wrapper": {
                "width": "",
                "class": "",
                "id": ""
            },
            "wpml_cf_preferences": 1,
            "collapsed": "",
            "min": 0,
            "max": 0,
            "layout": "block",
            "button_label": "",
            "sub_fields": [
                {
                    "key": "field_629e381e37bf8",
                    "label": "Heading",
                    "name": "heading",
                    "type": "text",
                    "instructions": "",
                    "required": 0,
                    "conditional_logic": 0,
                    "wrapper": {
                        "width": "",
                        "class": "",
                        "id": ""
                    },
                    "wpml_cf_preferences": 1,
                    "default_value": "",
                    "placeholder": "",
                    "prepend": "",
                    "append": "",
                    "maxlength": ""
                },
                {
                    "key": "field_62cd8f019611d",
                    "label": "Body",
                    "name": "body",
                    "type": "wysiwyg",
                    "instructions": "",
                    "required": 0,
                    "conditional_logic": 0,
                    "wrapper": {
                        "width": "",
                        "class": "",
                        "id": ""
                    },
                    "default_value": "",
                    "tabs": "all",
                    "toolbar": "full",
                    "media_upload": 1,
                    "delay": 0,
                    "wpml_cf_preferences": 1
                },
                {
                    "key": "field_629e382437bf9",
                    "label": "Email",
                    "name": "email",
                    "type": "link",
                    "instructions": "",
                    "required": 0,
                    "conditional_logic": 0,
                    "wrapper": {
                        "width": "",
                        "class": "",
                        "id": ""
                    },
                    "return_format": "array",
                    "wpml_cf_preferences": 1
                },
                {
                    "key": "field_629e382e37bfa",
                    "label": "Phone Number",
                    "name": "phone_number",
                    "type": "link",
                    "instructions": "",
                    "required": 0,
                    "conditional_logic": 0,
                    "wrapper": {
                        "width": "",
                        "class": "",
                        "id": ""
                    },
                    "return_format": "array",
                    "wpml_cf_preferences": 1
                }
            ]
        },
        {
            "key": "field_629e383737bfb",
            "label": "CTA 1",
            "name": "cta_1",
            "type": "link",
            "instructions": "",
            "required": 0,
            "conditional_logic": 0,
            "wrapper": {
                "width": "",
                "class": "",
                "id": ""
            },
            "return_format": "array",
            "wpml_cf_preferences": 1
        },
        {
            "key": "field_629e383b37bfc",
            "label": "CTA 2",
            "name": "cta_2",
            "type": "link",
            "instructions": "",
            "required": 0,
            "conditional_logic": 0,
            "wrapper": {
                "width": "",
                "class": "",
                "id": ""
            },
            "return_format": "array",
            "wpml_cf_preferences": 1
        }
    ],
    "location": [
        [
            {
                "param": "block",
                "operator": "==",
                "value": "acf\/contact-details"
            }
        ]
    ],
    "menu_order": 0,
    "position": "normal",
    "style": "default",
    "label_placement": "top",
    "instruction_placement": "label",
    "hide_on_screen": "",
    "active": true,
    "description": "",
    "show_in_rest": 0,
    "modified": 1657638667
}