{
    "key": "group_629f9906ce807",
    "title": "Block Options",
    "fields": [
        {
            "key": "field_629f990e6b037",
            "label": "Dark Background",
            "name": "dark_background",
            "type": "true_false",
            "instructions": "",
            "required": 0,
            "conditional_logic": 0,
            "wrapper": {
                "width": "",
                "class": "",
                "id": ""
            },
            "message": "",
            "default_value": 0,
            "ui": 1,
            "ui_on_text": "",
            "ui_off_text": "",
            "wpml_cf_preferences": 1
        },
        {
            "key": "field_629fb4f10ae3e",
            "label": "Centered Text",
            "name": "centered",
            "type": "true_false",
            "instructions": "",
            "required": 0,
            "conditional_logic": 0,
            "wrapper": {
                "width": "",
                "class": "",
                "id": ""
            },
            "wpml_cf_preferences": 1,
            "message": "",
            "default_value": 0,
            "ui": 1,
            "ui_on_text": "",
            "ui_off_text": ""
        }
    ],
    "location": [
        [
            {
                "param": "block",
                "operator": "==",
                "value": "acf\/text-columns"
            }
        ],
        [
            {
                "param": "block",
                "operator": "==",
                "value": "acf\/text"
            }
        ]
    ],
    "menu_order": 2,
    "position": "normal",
    "style": "default",
    "label_placement": "top",
    "instruction_placement": "label",
    "hide_on_screen": "",
    "active": true,
    "description": "",
    "show_in_rest": 0,
    "modified": 1655124037
}